sentd/__init__.py
sentd/client.py
sentd/exceptions.py
sentd/py.typed
sentd/types.py
sentd-1.0.0.dist-info/METADATA
sentd-1.0.0.dist-info/WHEEL
sentd-1.0.0.dist-info/RECORD
