Metadata-Version: 2.4
Name: sentd
Version: 1.0.0
Summary: Official Python SDK for the SENTD Email API
Project-URL: Homepage, https://sentd.io
Project-URL: Documentation, https://sentd.io/docs
Project-URL: Repository, https://github.com/sentd/sentd-python
Project-URL: Changelog, https://github.com/sentd/sentd-python/releases
Author-email: SENTD <support@sentd.io>
License-Expression: MIT
Keywords: api,email,email-api,sdk,sentd,transactional
Classifier: Development Status :: 5 - Production/Stable
Classifier: Intended Audience :: Developers
Classifier: License :: OSI Approved :: MIT License
Classifier: Operating System :: OS Independent
Classifier: Programming Language :: Python :: 3
Classifier: Programming Language :: Python :: 3.8
Classifier: Programming Language :: Python :: 3.9
Classifier: Programming Language :: Python :: 3.10
Classifier: Programming Language :: Python :: 3.11
Classifier: Programming Language :: Python :: 3.12
Classifier: Topic :: Communications :: Email
Classifier: Topic :: Software Development :: Libraries :: Python Modules
Classifier: Typing :: Typed
Requires-Python: >=3.8
Requires-Dist: httpx>=0.24.0
Requires-Dist: pydantic>=2.0.0
Provides-Extra: dev
Requires-Dist: mypy>=1.0.0; extra == 'dev'
Requires-Dist: pytest-asyncio>=0.21.0; extra == 'dev'
Requires-Dist: pytest-httpx>=0.22.0; extra == 'dev'
Requires-Dist: pytest>=7.0.0; extra == 'dev'
Requires-Dist: ruff>=0.1.0; extra == 'dev'
